{"firstDoseTotal": 6915677, "firstDosePercent": "95.3%", "secondDoseTotal": 6799640, "secondDosePercent": "93.9%", "thirdDoseTotal": 5855131, "thirdDosePercent": "84.5%", "fourthDoseTotal": 1131730, "fifthDoseTotal": 89133, "latestDaily": 405, "sevenDayAvg": 909, "firstDoseDaily": 9, "secondDoseDaily": 18, "thirdDoseDaily": 22, "fourthDoseDaily": 174, "fifthDoseDaily": 180, "totalDosesAdministered": 20791338, "firstDose635MthTotal": 27309, "secondDose635MthTotal": 18098, "thirdDose635MthTotal": 2248, "fourthDose635MthTotal": 0}