{"firstDoseTotal": 6917010, "firstDosePercent": "95.4%", "secondDoseTotal": 6801004, "secondDosePercent": "93.9%", "thirdDoseTotal": 5857702, "thirdDosePercent": "84.5%", "fourthDoseTotal": 1151469, "fifthDoseTotal": 107436, "latestDaily": 485, "sevenDayAvg": 392, "firstDoseDaily": 13, "secondDoseDaily": 21, "thirdDoseDaily": 19, "fourthDoseDaily": 239, "fifthDoseDaily": 162, "totalDosesAdministered": 20836677, "firstDose635MthTotal": 27832, "secondDose635MthTotal": 18586, "thirdDose635MthTotal": 2513, "fourthDose635MthTotal": 0}