{"firstDoseTotal": 6914411, "firstDosePercent": "94.6%", "secondDoseTotal": 6797418, "secondDosePercent": "93.1%", "thirdDoseTotal": 5846276, "thirdDosePercent": "83.9%", "fourthDoseTotal": 1093933, "fifthDoseTotal": 69011, "latestDaily": 1446, "sevenDayAvg": 1407, "firstDoseDaily": 34, "secondDoseDaily": 55, "thirdDoseDaily": 214, "fourthDoseDaily": 743, "fifthDoseDaily": 400, "totalDosesAdministered": 20721049, "firstDose635MthTotal": 26803, "secondDose635MthTotal": 17269, "thirdDose635MthTotal": 1965, "fourthDose635MthTotal": 0}