{"firstDoseTotal": 6916665, "firstDosePercent": "95.3%", "secondDoseTotal": 6800655, "secondDosePercent": "93.9%", "thirdDoseTotal": 5857161, "thirdDosePercent": "84.5%", "fourthDoseTotal": 1146940, "fifthDoseTotal": 102614, "latestDaily": 41, "sevenDayAvg": 543, "firstDoseDaily": 4, "secondDoseDaily": 5, "thirdDoseDaily": 8, "fourthDoseDaily": 10, "fifthDoseDaily": 10, "totalDosesAdministered": 20824991, "firstDose635MthTotal": 27703, "secondDose635MthTotal": 18442, "thirdDose635MthTotal": 2445, "fourthDose635MthTotal": 0}