[{"age": "Aged 12-19", "totalPopulation": 448800, "firstDose": {"sinovac": 15304, "biontech": 314433, "total": 329737}, "secondDose": {"sinovac": 14138, "biontech": 238692, "total": 252830}, "thirdDose": {"sinovac": 33, "biontech": 36, "total": 69}}, {"age": "Aged 20-29", "totalPopulation": 808700, "firstDose": {"sinovac": 109713, "biontech": 513046, "total": 622759}, "secondDose": {"sinovac": 105644, "biontech": 494601, "total": 600245}, "thirdDose": {"sinovac": 839, "biontech": 1393, "total": 2232}}, {"age": "Aged 30-39", "totalPopulation": 1126300, "firstDose": {"sinovac": 219868, "biontech": 652868, "total": 872736}, "secondDose": {"sinovac": 212237, "biontech": 634095, "total": 846332}, "thirdDose": {"sinovac": 2979, "biontech": 4536, "total": 7515}}, {"age": "Aged 40-49", "totalPopulation": 1142500, "firstDose": {"sinovac": 366264, "biontech": 602435, "total": 968699}, "secondDose": {"sinovac": 356898, "biontech": 590401, "total": 947299}, "thirdDose": {"sinovac": 7585, "biontech": 8099, "total": 15684}}, {"age": "Aged 50-59", "totalPopulation": 1174200, "firstDose": {"sinovac": 442081, "biontech": 486293, "total": 928374}, "secondDose": {"sinovac": 430853, "biontech": 476141, "total": 906994}, "thirdDose": {"sinovac": 10369, "biontech": 10501, "total": 20870}}, {"age": "Aged 60-69", "totalPopulation": 1071800, "firstDose": {"sinovac": 373278, "biontech": 307222, "total": 680500}, "secondDose": {"sinovac": 359900, "biontech": 298891, "total": 658791}, "thirdDose": {"sinovac": 23939, "biontech": 26815, "total": 50754}}, {"age": "Aged 70-79", "totalPopulation": 560500, "firstDose": {"sinovac": 149781, "biontech": 103085, "total": 252866}, "secondDose": {"sinovac": 141805, "biontech": 98992, "total": 240797}, "thirdDose": {"sinovac": 10815, "biontech": 9520, "total": 20335}}, {"age": "Aged 80 and above", "totalPopulation": 401800, "firstDose": {"sinovac": 46922, "biontech": 24879, "total": 71801}, "secondDose": {"sinovac": 41840, "biontech": 23012, "total": 64852}, "thirdDose": {"sinovac": 2674, "biontech": 1781, "total": 4455}}]