[{"age": "Aged 0-2", "totalPopulation": 104000, "firstDose": {"sinovac": 20425, "biontech": 574, "total": 20999}, "secondDose": {"sinovac": 12118, "biontech": 3, "total": 12121}, "thirdDose": {"sinovac": 9, "biontech": 1, "total": 10}}, {"age": "Aged 3-11", "totalPopulation": 502600, "firstDose": {"sinovac": 337201, "biontech": 103011, "total": 440212}, "secondDose": {"sinovac": 303465, "biontech": 78513, "total": 381978}, "thirdDose": {"sinovac": 144878, "biontech": 1150, "total": 146028}}, {"age": "Aged 12-19", "totalPopulation": 447300, "firstDose": {"sinovac": 69462, "biontech": 382225, "total": 451687}, "secondDose": {"sinovac": 72086, "biontech": 372369, "total": 444455}, "thirdDose": {"sinovac": 79846, "biontech": 256220, "total": 336066}}, {"age": "Aged 20-29", "totalPopulation": 771900, "firstDose": {"sinovac": 144937, "biontech": 623712, "total": 768649}, "secondDose": {"sinovac": 141563, "biontech": 613649, "total": 755212}, "thirdDose": {"sinovac": 106147, "biontech": 498205, "total": 604352}}, {"age": "Aged 30-39", "totalPopulation": 1094500, "firstDose": {"sinovac": 303636, "biontech": 800729, "total": 1104365}, "secondDose": {"sinovac": 296905, "biontech": 792702, "total": 1089607}, "thirdDose": {"sinovac": 214951, "biontech": 685321, "total": 900272}}, {"age": "Aged 40-49", "totalPopulation": 1160300, "firstDose": {"sinovac": 471433, "biontech": 699669, "total": 1171102}, "secondDose": {"sinovac": 466016, "biontech": 697062, "total": 1163078}, "thirdDose": {"sinovac": 346158, "biontech": 684605, "total": 1030763}}, {"age": "Aged 50-59", "totalPopulation": 1191300, "firstDose": {"sinovac": 583340, "biontech": 577440, "total": 1160780}, "secondDose": {"sinovac": 577838, "biontech": 574536, "total": 1152374}, "thirdDose": {"sinovac": 440918, "biontech": 608712, "total": 1049630}}, {"age": "Aged 60-69", "totalPopulation": 1122100, "firstDose": {"sinovac": 590658, "biontech": 411134, "total": 1001792}, "secondDose": {"sinovac": 584574, "biontech": 409703, "total": 994277}, "thirdDose": {"sinovac": 469194, "biontech": 460831, "total": 930025}}, {"age": "Aged 70-79", "totalPopulation": 591300, "firstDose": {"sinovac": 332208, "biontech": 160512, "total": 492720}, "secondDose": {"sinovac": 329493, "biontech": 160150, "total": 489643}, "thirdDose": {"sinovac": 283223, "biontech": 183720, "total": 466943}}, {"age": "Aged 80 and above", "totalPopulation": 398200, "firstDose": {"sinovac": 227824, "biontech": 57502, "total": 285326}, "secondDose": {"sinovac": 220136, "biontech": 56366, "total": 276502}, "thirdDose": {"sinovac": 185790, "biontech": 60336, "total": 246126}}]