[{"age": "Aged 0-2", "totalPopulation": 104000, "firstDose": {"sinovac": 18633, "biontech": 0, "total": 18633}, "secondDose": {"sinovac": 9581, "biontech": 0, "total": 9581}, "thirdDose": {"sinovac": 6, "biontech": 0, "total": 6}}, {"age": "Aged 3-11", "totalPopulation": 502600, "firstDose": {"sinovac": 334523, "biontech": 101288, "total": 435811}, "secondDose": {"sinovac": 293348, "biontech": 75473, "total": 368821}, "thirdDose": {"sinovac": 134089, "biontech": 912, "total": 135001}}, {"age": "Aged 12-19", "totalPopulation": 447300, "firstDose": {"sinovac": 69222, "biontech": 382025, "total": 451247}, "secondDose": {"sinovac": 71139, "biontech": 370755, "total": 441894}, "thirdDose": {"sinovac": 73988, "biontech": 240792, "total": 314780}}, {"age": "Aged 20-29", "totalPopulation": 771900, "firstDose": {"sinovac": 144577, "biontech": 623351, "total": 767928}, "secondDose": {"sinovac": 140896, "biontech": 612551, "total": 753447}, "thirdDose": {"sinovac": 102864, "biontech": 489524, "total": 592388}}, {"age": "Aged 30-39", "totalPopulation": 1094500, "firstDose": {"sinovac": 302944, "biontech": 800266, "total": 1103210}, "secondDose": {"sinovac": 295631, "biontech": 791317, "total": 1086948}, "thirdDose": {"sinovac": 208852, "biontech": 675361, "total": 884213}}, {"age": "Aged 40-49", "totalPopulation": 1160300, "firstDose": {"sinovac": 470898, "biontech": 699430, "total": 1170328}, "secondDose": {"sinovac": 464930, "biontech": 696423, "total": 1161353}, "thirdDose": {"sinovac": 339999, "biontech": 678282, "total": 1018281}}, {"age": "Aged 50-59", "totalPopulation": 1191300, "firstDose": {"sinovac": 582752, "biontech": 577211, "total": 1159963}, "secondDose": {"sinovac": 576454, "biontech": 573949, "total": 1150403}, "thirdDose": {"sinovac": 433210, "biontech": 603027, "total": 1036237}}, {"age": "Aged 60-69", "totalPopulation": 1122100, "firstDose": {"sinovac": 589638, "biontech": 410873, "total": 1000511}, "secondDose": {"sinovac": 582446, "biontech": 409028, "total": 991474}, "thirdDose": {"sinovac": 458619, "biontech": 455781, "total": 914400}}, {"age": "Aged 70-79", "totalPopulation": 591300, "firstDose": {"sinovac": 331312, "biontech": 160361, "total": 491673}, "secondDose": {"sinovac": 327651, "biontech": 159736, "total": 487387}, "thirdDose": {"sinovac": 273791, "biontech": 180953, "total": 454744}}, {"age": "Aged 80 and above", "totalPopulation": 398200, "firstDose": {"sinovac": 226671, "biontech": 57383, "total": 284054}, "secondDose": {"sinovac": 218053, "biontech": 56076, "total": 274129}, "thirdDose": {"sinovac": 175779, "biontech": 58728, "total": 234507}}]