[{"age": "Aged 0-2", "totalPopulation": 104000, "firstDose": {"sinovac": 17406, "biontech": 0, "total": 17406}, "secondDose": {"sinovac": 6302, "biontech": 0, "total": 6302}, "thirdDose": {"sinovac": 6, "biontech": 0, "total": 6}}, {"age": "Aged 3-11", "totalPopulation": 502600, "firstDose": {"sinovac": 327470, "biontech": 98104, "total": 425574}, "secondDose": {"sinovac": 281807, "biontech": 72710, "total": 354517}, "thirdDose": {"sinovac": 108788, "biontech": 644, "total": 109432}}, {"age": "Aged 12-19", "totalPopulation": 447300, "firstDose": {"sinovac": 68949, "biontech": 381751, "total": 450700}, "secondDose": {"sinovac": 70178, "biontech": 368536, "total": 438714}, "thirdDose": {"sinovac": 63915, "biontech": 213559, "total": 277474}}, {"age": "Aged 20-29", "totalPopulation": 771900, "firstDose": {"sinovac": 144252, "biontech": 622927, "total": 767179}, "secondDose": {"sinovac": 140283, "biontech": 611347, "total": 751630}, "thirdDose": {"sinovac": 97921, "biontech": 475297, "total": 573218}}, {"age": "Aged 30-39", "totalPopulation": 1094500, "firstDose": {"sinovac": 302297, "biontech": 799757, "total": 1102054}, "secondDose": {"sinovac": 294535, "biontech": 789876, "total": 1084411}, "thirdDose": {"sinovac": 198617, "biontech": 658943, "total": 857560}}, {"age": "Aged 40-49", "totalPopulation": 1160300, "firstDose": {"sinovac": 470401, "biontech": 699227, "total": 1169628}, "secondDose": {"sinovac": 463891, "biontech": 695729, "total": 1159620}, "thirdDose": {"sinovac": 328736, "biontech": 667697, "total": 996433}}, {"age": "Aged 50-59", "totalPopulation": 1191300, "firstDose": {"sinovac": 582231, "biontech": 577020, "total": 1159251}, "secondDose": {"sinovac": 575132, "biontech": 573323, "total": 1148455}, "thirdDose": {"sinovac": 420830, "biontech": 594098, "total": 1014928}}, {"age": "Aged 60-69", "totalPopulation": 1122100, "firstDose": {"sinovac": 588817, "biontech": 410656, "total": 999473}, "secondDose": {"sinovac": 580417, "biontech": 408328, "total": 988745}, "thirdDose": {"sinovac": 443677, "biontech": 447957, "total": 891634}}, {"age": "Aged 70-79", "totalPopulation": 591300, "firstDose": {"sinovac": 330617, "biontech": 160241, "total": 490858}, "secondDose": {"sinovac": 325961, "biontech": 159367, "total": 485328}, "thirdDose": {"sinovac": 262432, "biontech": 177101, "total": 439533}}, {"age": "Aged 80 and above", "totalPopulation": 398200, "firstDose": {"sinovac": 225875, "biontech": 57297, "total": 283172}, "secondDose": {"sinovac": 216252, "biontech": 55829, "total": 272081}, "thirdDose": {"sinovac": 164887, "biontech": 56966, "total": 221853}}]