[{"age": "Aged 0-2", "totalPopulation": 104000, "firstDose": {"sinovac": 23997, "biontech": 2947, "total": 26944}, "secondDose": {"sinovac": 16250, "biontech": 1305, "total": 17555}, "thirdDose": {"sinovac": 1788, "biontech": 251, "total": 2039}}, {"age": "Aged 3-11", "totalPopulation": 502600, "firstDose": {"sinovac": 339607, "biontech": 105457, "total": 445064}, "secondDose": {"sinovac": 314576, "biontech": 83338, "total": 397914}, "thirdDose": {"sinovac": 156590, "biontech": 2580, "total": 159170}}, {"age": "Aged 12-19", "totalPopulation": 447300, "firstDose": {"sinovac": 69588, "biontech": 382401, "total": 451989}, "secondDose": {"sinovac": 72864, "biontech": 373432, "total": 446296}, "thirdDose": {"sinovac": 83209, "biontech": 263302, "total": 346511}}, {"age": "Aged 20-29", "totalPopulation": 771900, "firstDose": {"sinovac": 145133, "biontech": 623977, "total": 769110}, "secondDose": {"sinovac": 142113, "biontech": 614726, "total": 756839}, "thirdDose": {"sinovac": 109280, "biontech": 510596, "total": 619876}}, {"age": "Aged 30-39", "totalPopulation": 1094500, "firstDose": {"sinovac": 303991, "biontech": 801150, "total": 1105141}, "secondDose": {"sinovac": 298064, "biontech": 794146, "total": 1092210}, "thirdDose": {"sinovac": 220308, "biontech": 700061, "total": 920369}}, {"age": "Aged 40-49", "totalPopulation": 1160300, "firstDose": {"sinovac": 471747, "biontech": 699939, "total": 1171686}, "secondDose": {"sinovac": 467056, "biontech": 697827, "total": 1164883}, "thirdDose": {"sinovac": 351948, "biontech": 695935, "total": 1047883}}, {"age": "Aged 50-59", "totalPopulation": 1191300, "firstDose": {"sinovac": 583733, "biontech": 577811, "total": 1161544}, "secondDose": {"sinovac": 578973, "biontech": 575417, "total": 1154390}, "thirdDose": {"sinovac": 448030, "biontech": 619344, "total": 1067374}}, {"age": "Aged 60-69", "totalPopulation": 1122100, "firstDose": {"sinovac": 591253, "biontech": 411525, "total": 1002778}, "secondDose": {"sinovac": 586410, "biontech": 410682, "total": 997092}, "thirdDose": {"sinovac": 478591, "biontech": 470291, "total": 948882}}, {"age": "Aged 70-79", "totalPopulation": 591300, "firstDose": {"sinovac": 332909, "biontech": 160804, "total": 493713}, "secondDose": {"sinovac": 331252, "biontech": 160817, "total": 492069}, "thirdDose": {"sinovac": 291671, "biontech": 188601, "total": 480272}}, {"age": "Aged 80 and above", "totalPopulation": 398200, "firstDose": {"sinovac": 229096, "biontech": 57734, "total": 286830}, "secondDose": {"sinovac": 222249, "biontech": 56764, "total": 279013}, "thirdDose": {"sinovac": 194746, "biontech": 62830, "total": 257576}}]