[{"age": "Aged 0-2", "totalPopulation": 91034, "firstDose": {"sinovac": 24190, "biontech": 3059, "total": 27249}, "secondDose": {"sinovac": 16484, "biontech": 1539, "total": 18023}, "thirdDose": {"sinovac": 1902, "biontech": 306, "total": 2208}}, {"age": "Aged 3-11", "totalPopulation": 484300, "firstDose": {"sinovac": 339596, "biontech": 105515, "total": 445111}, "secondDose": {"sinovac": 314618, "biontech": 83531, "total": 398149}, "thirdDose": {"sinovac": 156790, "biontech": 2706, "total": 159496}}, {"age": "Aged 12-19", "totalPopulation": 442700, "firstDose": {"sinovac": 69591, "biontech": 382420, "total": 452011}, "secondDose": {"sinovac": 72876, "biontech": 373461, "total": 446337}, "thirdDose": {"sinovac": 83256, "biontech": 263482, "total": 346738}}, {"age": "Aged 20-29", "totalPopulation": 720200, "firstDose": {"sinovac": 145139, "biontech": 623989, "total": 769128}, "secondDose": {"sinovac": 142117, "biontech": 614751, "total": 756868}, "thirdDose": {"sinovac": 109402, "biontech": 511006, "total": 620408}}, {"age": "Aged 30-39", "totalPopulation": 1065900, "firstDose": {"sinovac": 303995, "biontech": 801176, "total": 1105171}, "secondDose": {"sinovac": 298087, "biontech": 794173, "total": 1092260}, "thirdDose": {"sinovac": 220519, "biontech": 700509, "total": 921028}}, {"age": "Aged 40-49", "totalPopulation": 1148400, "firstDose": {"sinovac": 471754, "biontech": 699964, "total": 1171718}, "secondDose": {"sinovac": 467071, "biontech": 697857, "total": 1164928}, "thirdDose": {"sinovac": 352170, "biontech": 696299, "total": 1048469}}, {"age": "Aged 50-59", "totalPopulation": 1168000, "firstDose": {"sinovac": 583746, "biontech": 577832, "total": 1161578}, "secondDose": {"sinovac": 578996, "biontech": 575434, "total": 1154430}, "thirdDose": {"sinovac": 448316, "biontech": 619715, "total": 1068031}}, {"age": "Aged 60-69", "totalPopulation": 1165400, "firstDose": {"sinovac": 591282, "biontech": 411524, "total": 1002806}, "secondDose": {"sinovac": 586443, "biontech": 410718, "total": 997161}, "thirdDose": {"sinovac": 478923, "biontech": 470603, "total": 949526}}, {"age": "Aged 70-79", "totalPopulation": 637500, "firstDose": {"sinovac": 332949, "biontech": 160813, "total": 493762}, "secondDose": {"sinovac": 331305, "biontech": 160850, "total": 492155}, "thirdDose": {"sinovac": 291925, "biontech": 188757, "total": 480682}}, {"age": "Aged 80 and above", "totalPopulation": 392700, "firstDose": {"sinovac": 229210, "biontech": 57757, "total": 286967}, "secondDose": {"sinovac": 222355, "biontech": 56786, "total": 279141}, "thirdDose": {"sinovac": 195166, "biontech": 62933, "total": 258099}}]